Metadata-Version: 2.1
Name: knapsack-pip
Version: 0.2
Summary: Knapsack problem solver
Home-page: https://github.com/Alieladi/knapsack-pip
Author: Ali El Adi
Author-email: alieladi@gmail.com
License: UNKNOWN
Keywords: knapsack backpack
Platform: UNKNOWN
Classifier: Programming Language :: Python :: 3
Classifier: License :: OSI Approved :: MIT License
Requires-Python: >=3
